ApiRequestManager/__init__.py
src/Config.py
src/ConfigPath.py
src/Pipelines.py
src/RequestFactory.py
src/__init__.py
src/instance_method_decorator.py
src/make_pipe.py
src/ApiConfig/ApiConfig.py
src/ApiConfig/UniqueDecorator.py
src/ApiConfig/__init__.py
src/ApiRequest/ApiRequest.py
src/ApiRequest/__init__.py
ApiRequestManager-1.0.5.dist-info/LICENSE
ApiRequestManager-1.0.5.dist-info/METADATA
ApiRequestManager-1.0.5.dist-info/WHEEL
ApiRequestManager-1.0.5.dist-info/top_level.txt
ApiRequestManager-1.0.5.dist-info/RECORD
