Metadata-Version: 2.1
Name: ApiRequestManager
Version: 1.0.5
Summary: Communicate with Apis is easy
Home-page: https://github.com/clemparpa/PyApiManager
Author: clemparpa
Author-email: clem.parpaillon@example.com
License: UNKNOWN
Platform: UNKNOWN
Classifier: Programming Language :: Python :: 3
Classifier: License :: OSI Approved :: MIT License
Classifier: Operating System :: OS Independent
Requires-Python: >=3.6
Requires-Dist: requests
